skiptir/__init__.py
skiptir/const.py
skiptir/main.py
skiptir/skiptir.py
skiptir/pyphen/COPYING.LGPL
skiptir/pyphen/__init__.py
skiptir/pyphen/dictionaries/hyph_is.dic
skiptir/pyphen/dictionaries/hyph_is_1985_corrected.dic
skiptir/pyphen/dictionaries/hyph_is_1985_unchanged_list.dic
skiptir/pyphen/dictionaries/hyph_is_2020_alpha.dic
skiptir/pyphen/dictionaries/hyph_is_2020_alpha2_extra.dic
skiptir/pyphen/dictionaries/hyph_is_JPind_1988.dic
skiptir-1.0.0.dist-info/licenses/LICENSE.md
skiptir-1.0.0.dist-info/METADATA
skiptir-1.0.0.dist-info/WHEEL
skiptir-1.0.0.dist-info/entry_points.txt
skiptir-1.0.0.dist-info/top_level.txt
skiptir-1.0.0.dist-info/RECORD
