Metadata-Version: 2.4
Name: skiptir
Version: 1.0.0
Summary: Hyphenate Icelandic text.
Author-email: Sveinbjorn Thordarson <sveinbjorn@sveinbjorn.org>, Kristján Rúnarsson <krunars@gmail.com>
Maintainer-email: Sveinbjorn Thordarson <sveinbjorn@sveinbjorn.org>
License-Expression: BSD-3-Clause
Project-URL: Repository, https://github.com/sveinbjornt/skiptir
Project-URL: Documentation, https://github.com/sveinbjornt/skiptir#readme
Project-URL: Issues, https://github.com/sveinbjornt/skiptir/issues
Project-URL: Changelog, https://github.com/sveinbjornt/skiptir#version-history
Keywords: icelandic,iceland,hyphenation
Classifier: Operating System :: OS Independent
Classifier: Development Status :: 5 - Production/Stable
Classifier: Intended Audience :: Developers
Classifier: Natural Language :: Icelandic
Classifier: Programming Language :: Python
Classifier: Programming Language :: Python :: 3
Classifier: Programming Language :: Python :: 3 :: Only
Classifier: Programming Language :: Python :: 3.9
Classifier: Programming Language :: Python :: 3.10
Classifier: Programming Language :: Python :: 3.11
Classifier: Programming Language :: Python :: 3.12
Classifier: Programming Language :: Python :: 3.13
Classifier: Programming Language :: Python :: 3.14
Classifier: Topic :: Software Development :: Libraries :: Python Modules
Classifier: Topic :: Utilities
Classifier: Topic :: Text Processing :: Linguistic
Requires-Python: >=3.9
License-File: LICENSE.md
Provides-Extra: dev
Requires-Dist: pytest==8.4.2; extra == "dev"
Requires-Dist: types-setuptools==80.9.0.20251223; extra == "dev"
Requires-Dist: ruff>=0.14.10; extra == "dev"
Requires-Dist: pyright>=1.1.407; extra == "dev"
Dynamic: license-file
